cookiecutter_pypackage_instance/__init__.py
cookiecutter_pypackage_instance/cookiecutter_pypackage_instance.py
cookiecutter_pypackage_instance/py.typed
cookiecutter_pypackage_instance-1.1.1.dist-info/LICENSE
cookiecutter_pypackage_instance-1.1.1.dist-info/METADATA
cookiecutter_pypackage_instance-1.1.1.dist-info/WHEEL
cookiecutter_pypackage_instance-1.1.1.dist-info/RECORD
