Metadata-Version: 2.1
Name: cookiecutter-pypackage-instance
Version: 1.1.1
Summary: 🐍 An awesome python package by the name Cookiecutter Pypackage Instance
Home-page: https://billsioros.github.io/cookiecutter-pypackage-instance
License: MIT
Author: Vasilis Sioros
Author-email: billsioros97@gmail.com
Requires-Python: >=3.7,<4.0
Classifier: License :: OSI Approved :: MIT License
Classifier: Programming Language :: Python
Classifier: Programming Language :: Python :: 3
Classifier: Programming Language :: Python :: 3.7
Classifier: Programming Language :: Python :: 3.8
Classifier: Programming Language :: Python :: 3.9
Classifier: Programming Language :: Python :: 3.10
Classifier: Programming Language :: Python :: 3.11
Classifier: Programming Language :: Python :: 3 :: Only
Project-URL: Bug Tracker, https://github.com/billsioros/cookiecutter-pypackage-instance/issues
Project-URL: Changelog, https://github.com/billsioros/cookiecutter-pypackage-instance/releases
Project-URL: Repository, https://github.com/billsioros/cookiecutter-pypackage-instance
